{
	"configurations" : 
	[
		{
			"directories" : 
			[
				{
					"build" : ".",
					"hasInstallRule" : true,
					"jsonFile" : "directory-.-9a3fec5e520688fa5978.json",
					"minimumCMakeVersion" : 
					{
						"string" : "2.8"
					},
					"projectIndex" : 0,
					"source" : ".",
					"targetIndexes" : 
					[
						0,
						1,
						2,
						3,
						4,
						5,
						6,
						7,
						8,
						9,
						10,
						11,
						12,
						13,
						14,
						15,
						16,
						17,
						18,
						19,
						20,
						21,
						22,
						23,
						24,
						25,
						26,
						27,
						28,
						29,
						30,
						31,
						32,
						33,
						34,
						35,
						36,
						37,
						38,
						39,
						40,
						41,
						42,
						43,
						44,
						45,
						46,
						47,
						48,
						49,
						50,
						51,
						52,
						53,
						54,
						55,
						56,
						57,
						58,
						59,
						60,
						61,
						62,
						63,
						64,
						65,
						66,
						67,
						68,
						69,
						70,
						71,
						72,
						73,
						74,
						75,
						76,
						77,
						78,
						79,
						80,
						81,
						82,
						83,
						84,
						85,
						86,
						87,
						88,
						89,
						90,
						91,
						92,
						93,
						94,
						95,
						96,
						97,
						98,
						99,
						100,
						101,
						102,
						103,
						104,
						105,
						106,
						107,
						108,
						109,
						110,
						111,
						112,
						113,
						114,
						115,
						116,
						117,
						118,
						119,
						120,
						121,
						122,
						123,
						124,
						125,
						126,
						127,
						128,
						129,
						130,
						131,
						132,
						133,
						134,
						135,
						136,
						137,
						138,
						139,
						140,
						141,
						142,
						143,
						144,
						145,
						146,
						147,
						148,
						149,
						150,
						151,
						152,
						153,
						154,
						155,
						156,
						157,
						158,
						159,
						160,
						161,
						162,
						163,
						164,
						165,
						166,
						167,
						168,
						169,
						170,
						171,
						172,
						173,
						174,
						175,
						176,
						177,
						178,
						179,
						180,
						181,
						182,
						183,
						184,
						185,
						186,
						187,
						188,
						189,
						190,
						191,
						192,
						193,
						194,
						195,
						196,
						197,
						198,
						199,
						200,
						201,
						202,
						203,
						204,
						205,
						206,
						207,
						208,
						209,
						210,
						211,
						212,
						213,
						214,
						215,
						216,
						217,
						218,
						219,
						220,
						221,
						222,
						223,
						224,
						225,
						226,
						227,
						228,
						229,
						230,
						231,
						232,
						233,
						234,
						235,
						236,
						237,
						238,
						239,
						240,
						241,
						242,
						243,
						244,
						245,
						246,
						247,
						248,
						249,
						250,
						251,
						252,
						253,
						254,
						255
					]
				}
			],
			"name" : "",
			"projects" : 
			[
				{
					"directoryIndexes" : 
					[
						0
					],
					"name" : "gazebo_models",
					"targetIndexes" : 
					[
						0,
						1,
						2,
						3,
						4,
						5,
						6,
						7,
						8,
						9,
						10,
						11,
						12,
						13,
						14,
						15,
						16,
						17,
						18,
						19,
						20,
						21,
						22,
						23,
						24,
						25,
						26,
						27,
						28,
						29,
						30,
						31,
						32,
						33,
						34,
						35,
						36,
						37,
						38,
						39,
						40,
						41,
						42,
						43,
						44,
						45,
						46,
						47,
						48,
						49,
						50,
						51,
						52,
						53,
						54,
						55,
						56,
						57,
						58,
						59,
						60,
						61,
						62,
						63,
						64,
						65,
						66,
						67,
						68,
						69,
						70,
						71,
						72,
						73,
						74,
						75,
						76,
						77,
						78,
						79,
						80,
						81,
						82,
						83,
						84,
						85,
						86,
						87,
						88,
						89,
						90,
						91,
						92,
						93,
						94,
						95,
						96,
						97,
						98,
						99,
						100,
						101,
						102,
						103,
						104,
						105,
						106,
						107,
						108,
						109,
						110,
						111,
						112,
						113,
						114,
						115,
						116,
						117,
						118,
						119,
						120,
						121,
						122,
						123,
						124,
						125,
						126,
						127,
						128,
						129,
						130,
						131,
						132,
						133,
						134,
						135,
						136,
						137,
						138,
						139,
						140,
						141,
						142,
						143,
						144,
						145,
						146,
						147,
						148,
						149,
						150,
						151,
						152,
						153,
						154,
						155,
						156,
						157,
						158,
						159,
						160,
						161,
						162,
						163,
						164,
						165,
						166,
						167,
						168,
						169,
						170,
						171,
						172,
						173,
						174,
						175,
						176,
						177,
						178,
						179,
						180,
						181,
						182,
						183,
						184,
						185,
						186,
						187,
						188,
						189,
						190,
						191,
						192,
						193,
						194,
						195,
						196,
						197,
						198,
						199,
						200,
						201,
						202,
						203,
						204,
						205,
						206,
						207,
						208,
						209,
						210,
						211,
						212,
						213,
						214,
						215,
						216,
						217,
						218,
						219,
						220,
						221,
						222,
						223,
						224,
						225,
						226,
						227,
						228,
						229,
						230,
						231,
						232,
						233,
						234,
						235,
						236,
						237,
						238,
						239,
						240,
						241,
						242,
						243,
						244,
						245,
						246,
						247,
						248,
						249,
						250,
						251,
						252,
						253,
						254,
						255
					]
				}
			],
			"targets" : 
			[
				{
					"directoryIndex" : 0,
					"id" : "ambulance::@6890427a1f51a3e7e1df",
					"jsonFile" : "target-ambulance-98f597a1233702c7abdf.json",
					"name" : "ambulance",
					"projectIndex" : 0
				},
				{
					"directoryIndex" : 0,
					"id" : "apartment::@6890427a1f51a3e7e1df",
					"jsonFile" : "target-apartment-ead63c367612b9ec009b.json",
					"name" : "apartment",
					"projectIndex" : 0
				},
				{
					"directoryIndex" : 0,
					"id" : "apollo15_landing_site_1000x1000::@6890427a1f51a3e7e1df",
					"jsonFile" : "target-apollo15_landing_site_1000x1000-29b74acc29ea9ae13948.json",
					"name" : "apollo15_landing_site_1000x1000",
					"projectIndex" : 0
				},
				{
					"directoryIndex" : 0,
					"id" : "arm_part::@6890427a1f51a3e7e1df",
					"jsonFile" : "target-arm_part-6932f997fbf82fec88a9.json",
					"name" : "arm_part",
					"projectIndex" : 0
				},
				{
					"directoryIndex" : 0,
					"id" : "arrow_red::@6890427a1f51a3e7e1df",
					"jsonFile" : "target-arrow_red-02e419ebbde29e63f5b7.json",
					"name" : "arrow_red",
					"projectIndex" : 0
				},
				{
					"directoryIndex" : 0,
					"id" : "asphalt_plane::@6890427a1f51a3e7e1df",
					"jsonFile" : "target-asphalt_plane-053335acf90d2c1b0045.json",
					"name" : "asphalt_plane",
					"projectIndex" : 0
				},
				{
					"directoryIndex" : 0,
					"id" : "asus_xtion_pro_camera::@6890427a1f51a3e7e1df",
					"jsonFile" : "target-asus_xtion_pro_camera-1461c125540a0f78572e.json",
					"name" : "asus_xtion_pro_camera",
					"projectIndex" : 0
				},
				{
					"directoryIndex" : 0,
					"id" : "ball_bearing::@6890427a1f51a3e7e1df",
					"jsonFile" : "target-ball_bearing-9f307b115869f92bcadb.json",
					"name" : "ball_bearing",
					"projectIndex" : 0
				},
				{
					"directoryIndex" : 0,
					"id" : "beer::@6890427a1f51a3e7e1df",
					"jsonFile" : "target-beer-9cf240ca1cadc5b08248.json",
					"name" : "beer",
					"projectIndex" : 0
				},
				{
					"directoryIndex" : 0,
					"id" : "bin_4_dropping_task::@6890427a1f51a3e7e1df",
					"jsonFile" : "target-bin_4_dropping_task-bfd625de95a41c73224c.json",
					"name" : "bin_4_dropping_task",
					"projectIndex" : 0
				},
				{
					"directoryIndex" : 0,
					"id" : "bookshelf::@6890427a1f51a3e7e1df",
					"jsonFile" : "target-bookshelf-d17c4829057ac111e956.json",
					"name" : "bookshelf",
					"projectIndex" : 0
				},
				{
					"directoryIndex" : 0,
					"id" : "bowl::@6890427a1f51a3e7e1df",
					"jsonFile" : "target-bowl-5cf52b65fb104e606715.json",
					"name" : "bowl",
					"projectIndex" : 0
				},
				{
					"directoryIndex" : 0,
					"id" : "box_target_green::@6890427a1f51a3e7e1df",
					"jsonFile" : "target-box_target_green-620efdccb5bc4c9ce355.json",
					"name" : "box_target_green",
					"projectIndex" : 0
				},
				{
					"directoryIndex" : 0,
					"id" : "box_target_red::@6890427a1f51a3e7e1df",
					"jsonFile" : "target-box_target_red-dd31710ce2d8b9a17969.json",
					"name" : "box_target_red",
					"projectIndex" : 0
				},
				{
					"directoryIndex" : 0,
					"id" : "breakable_test::@6890427a1f51a3e7e1df",
					"jsonFile" : "target-breakable_test-4af1ca6da3ff13f271bc.json",
					"name" : "breakable_test",
					"projectIndex" : 0
				},
				{
					"directoryIndex" : 0,
					"id" : "brick_box_3x1x3::@6890427a1f51a3e7e1df",
					"jsonFile" : "target-brick_box_3x1x3-e8f5a12ab51d0df0f87a.json",
					"name" : "brick_box_3x1x3",
					"projectIndex" : 0
				},
				{
					"directoryIndex" : 0,
					"id" : "bus::@6890427a1f51a3e7e1df",
					"jsonFile" : "target-bus-516b65aef66993d4f4a4.json",
					"name" : "bus",
					"projectIndex" : 0
				},
				{
					"directoryIndex" : 0,
					"id" : "bus_stop::@6890427a1f51a3e7e1df",
					"jsonFile" : "target-bus_stop-23833f286d62e159e842.json",
					"name" : "bus_stop",
					"projectIndex" : 0
				},
				{
					"directoryIndex" : 0,
					"id" : "cabinet::@6890427a1f51a3e7e1df",
					"jsonFile" : "target-cabinet-e7d59c3a5745feceac51.json",
					"name" : "cabinet",
					"projectIndex" : 0
				},
				{
					"directoryIndex" : 0,
					"id" : "cafe::@6890427a1f51a3e7e1df",
					"jsonFile" : "target-cafe-9a3bec71653b2cfcacbb.json",
					"name" : "cafe",
					"projectIndex" : 0
				},
				{
					"directoryIndex" : 0,
					"id" : "cafe_table::@6890427a1f51a3e7e1df",
					"jsonFile" : "target-cafe_table-583897de2efeedd33842.json",
					"name" : "cafe_table",
					"projectIndex" : 0
				},
				{
					"directoryIndex" : 0,
					"id" : "calibration_plane::@6890427a1f51a3e7e1df",
					"jsonFile" : "target-calibration_plane-224ab76f0c9077a1a6a3.json",
					"name" : "calibration_plane",
					"projectIndex" : 0
				},
				{
					"directoryIndex" : 0,
					"id" : "camera::@6890427a1f51a3e7e1df",
					"jsonFile" : "target-camera-b32e25390c8ddf9a4996.json",
					"name" : "camera",
					"projectIndex" : 0
				},
				{
					"directoryIndex" : 0,
					"id" : "car_wheel::@6890427a1f51a3e7e1df",
					"jsonFile" : "target-car_wheel-949fc6d3dafe4e597239.json",
					"name" : "car_wheel",
					"projectIndex" : 0
				},
				{
					"directoryIndex" : 0,
					"id" : "cardboard_box::@6890427a1f51a3e7e1df",
					"jsonFile" : "target-cardboard_box-36a3433b04a11d46b87a.json",
					"name" : "cardboard_box",
					"projectIndex" : 0
				},
				{
					"directoryIndex" : 0,
					"id" : "cart_front_steer::@6890427a1f51a3e7e1df",
					"jsonFile" : "target-cart_front_steer-dc758aef197cad85bdb2.json",
					"name" : "cart_front_steer",
					"projectIndex" : 0
				},
				{
					"directoryIndex" : 0,
					"id" : "cart_rigid_suspension::@6890427a1f51a3e7e1df",
					"jsonFile" : "target-cart_rigid_suspension-dbda80a07b4ae21bd13f.json",
					"name" : "cart_rigid_suspension",
					"projectIndex" : 0
				},
				{
					"directoryIndex" : 0,
					"id" : "cart_soft_suspension::@6890427a1f51a3e7e1df",
					"jsonFile" : "target-cart_soft_suspension-a11fc406afc6e7aa4833.json",
					"name" : "cart_soft_suspension",
					"projectIndex" : 0
				},
				{
					"directoryIndex" : 0,
					"id" : "cessna::@6890427a1f51a3e7e1df",
					"jsonFile" : "target-cessna-02539c5ff394412b0a42.json",
					"name" : "cessna",
					"projectIndex" : 0
				},
				{
					"directoryIndex" : 0,
					"id" : "checkerboard_plane::@6890427a1f51a3e7e1df",
					"jsonFile" : "target-checkerboard_plane-9d696978214595ebc2dc.json",
					"name" : "checkerboard_plane",
					"projectIndex" : 0
				},
				{
					"directoryIndex" : 0,
					"id" : "cinder_block::@6890427a1f51a3e7e1df",
					"jsonFile" : "target-cinder_block-df0ed28a37465d59a771.json",
					"name" : "cinder_block",
					"projectIndex" : 0
				},
				{
					"directoryIndex" : 0,
					"id" : "cinder_block_2::@6890427a1f51a3e7e1df",
					"jsonFile" : "target-cinder_block_2-d155cd2e838bedaaa735.json",
					"name" : "cinder_block_2",
					"projectIndex" : 0
				},
				{
					"directoryIndex" : 0,
					"id" : "cinder_block_wide::@6890427a1f51a3e7e1df",
					"jsonFile" : "target-cinder_block_wide-1a670766f91db88143d2.json",
					"name" : "cinder_block_wide",
					"projectIndex" : 0
				},
				{
					"directoryIndex" : 0,
					"id" : "cloverleaf_interchange::@6890427a1f51a3e7e1df",
					"jsonFile" : "target-cloverleaf_interchange-a024c685fd75e031820a.json",
					"name" : "cloverleaf_interchange",
					"projectIndex" : 0
				},
				{
					"directoryIndex" : 0,
					"id" : "coke_can::@6890427a1f51a3e7e1df",
					"jsonFile" : "target-coke_can-07c1f835ce18cff59128.json",
					"name" : "coke_can",
					"projectIndex" : 0
				},
				{
					"directoryIndex" : 0,
					"id" : "collapsed_fire_station::@6890427a1f51a3e7e1df",
					"jsonFile" : "target-collapsed_fire_station-23b317ef80963b09c547.json",
					"name" : "collapsed_fire_station",
					"projectIndex" : 0
				},
				{
					"directoryIndex" : 0,
					"id" : "collapsed_house::@6890427a1f51a3e7e1df",
					"jsonFile" : "target-collapsed_house-3111a385308e4ead54d2.json",
					"name" : "collapsed_house",
					"projectIndex" : 0
				},
				{
					"directoryIndex" : 0,
					"id" : "collapsed_industrial::@6890427a1f51a3e7e1df",
					"jsonFile" : "target-collapsed_industrial-cbb9554263ee11af21a2.json",
					"name" : "collapsed_industrial",
					"projectIndex" : 0
				},
				{
					"directoryIndex" : 0,
					"id" : "collapsed_police_station::@6890427a1f51a3e7e1df",
					"jsonFile" : "target-collapsed_police_station-5f51eee4571b530c35f3.json",
					"name" : "collapsed_police_station",
					"projectIndex" : 0
				},
				{
					"directoryIndex" : 0,
					"id" : "construction_barrel::@6890427a1f51a3e7e1df",
					"jsonFile" : "target-construction_barrel-1f37806d56b4623c2e04.json",
					"name" : "construction_barrel",
					"projectIndex" : 0
				},
				{
					"directoryIndex" : 0,
					"id" : "construction_cone::@6890427a1f51a3e7e1df",
					"jsonFile" : "target-construction_cone-ebb1a29471911ef4af6c.json",
					"name" : "construction_cone",
					"projectIndex" : 0
				},
				{
					"directoryIndex" : 0,
					"id" : "control_console::@6890427a1f51a3e7e1df",
					"jsonFile" : "target-control_console-69b74ab6d319ec3b8a71.json",
					"name" : "control_console",
					"projectIndex" : 0
				},
				{
					"directoryIndex" : 0,
					"id" : "cordless_drill::@6890427a1f51a3e7e1df",
					"jsonFile" : "target-cordless_drill-87a6ca9786eb9859b28d.json",
					"name" : "cordless_drill",
					"projectIndex" : 0
				},
				{
					"directoryIndex" : 0,
					"id" : "create::@6890427a1f51a3e7e1df",
					"jsonFile" : "target-create-8d967f215fd603585f5b.json",
					"name" : "create",
					"projectIndex" : 0
				},
				{
					"directoryIndex" : 0,
					"id" : "cricket_ball::@6890427a1f51a3e7e1df",
					"jsonFile" : "target-cricket_ball-6292f6b1a16653d15f2a.json",
					"name" : "cricket_ball",
					"projectIndex" : 0
				},
				{
					"directoryIndex" : 0,
					"id" : "cross_joint_part::@6890427a1f51a3e7e1df",
					"jsonFile" : "target-cross_joint_part-6d038eb0fa47b606a5eb.json",
					"name" : "cross_joint_part",
					"projectIndex" : 0
				},
				{
					"directoryIndex" : 0,
					"id" : "cube_20k::@6890427a1f51a3e7e1df",
					"jsonFile" : "target-cube_20k-9ed4075a8291b9f621b6.json",
					"name" : "cube_20k",
					"projectIndex" : 0
				},
				{
					"directoryIndex" : 0,
					"id" : "demo_joint_damping::@6890427a1f51a3e7e1df",
					"jsonFile" : "target-demo_joint_damping-a876bf12d77c89ac7545.json",
					"name" : "demo_joint_damping",
					"projectIndex" : 0
				},
				{
					"directoryIndex" : 0,
					"id" : "demo_joint_friction::@6890427a1f51a3e7e1df",
					"jsonFile" : "target-demo_joint_friction-e0d2feaa221b1535d46b.json",
					"name" : "demo_joint_friction",
					"projectIndex" : 0
				},
				{
					"directoryIndex" : 0,
					"id" : "demo_joint_stiffness::@6890427a1f51a3e7e1df",
					"jsonFile" : "target-demo_joint_stiffness-7b0a4d6585ce9e10c0ab.json",
					"name" : "demo_joint_stiffness",
					"projectIndex" : 0
				},
				{
					"directoryIndex" : 0,
					"id" : "demo_joint_types::@6890427a1f51a3e7e1df",
					"jsonFile" : "target-demo_joint_types-bb4128f3e411e479ef8e.json",
					"name" : "demo_joint_types",
					"projectIndex" : 0
				},
				{
					"directoryIndex" : 0,
					"id" : "depth_camera::@6890427a1f51a3e7e1df",
					"jsonFile" : "target-depth_camera-966589250d8cfaf20940.json",
					"name" : "depth_camera",
					"projectIndex" : 0
				},
				{
					"directoryIndex" : 0,
					"id" : "disk_part::@6890427a1f51a3e7e1df",
					"jsonFile" : "target-disk_part-d7fadfbe84da98bd00fa.json",
					"name" : "disk_part",
					"projectIndex" : 0
				},
				{
					"directoryIndex" : 0,
					"id" : "door_handle::@6890427a1f51a3e7e1df",
					"jsonFile" : "target-door_handle-f0d294ff4ec63e59ea75.json",
					"name" : "door_handle",
					"projectIndex" : 0
				},
				{
					"directoryIndex" : 0,
					"id" : "double_pendulum_with_base::@6890427a1f51a3e7e1df",
					"jsonFile" : "target-double_pendulum_with_base-ed9044725e94239f13b4.json",
					"name" : "double_pendulum_with_base",
					"projectIndex" : 0
				},
				{
					"directoryIndex" : 0,
					"id" : "drc_practice_2x4::@6890427a1f51a3e7e1df",
					"jsonFile" : "target-drc_practice_2x4-e8df966b56e7686b6799.json",
					"name" : "drc_practice_2x4",
					"projectIndex" : 0
				},
				{
					"directoryIndex" : 0,
					"id" : "drc_practice_2x6::@6890427a1f51a3e7e1df",
					"jsonFile" : "target-drc_practice_2x6-a591ed666b84e035894d.json",
					"name" : "drc_practice_2x6",
					"projectIndex" : 0
				},
				{
					"directoryIndex" : 0,
					"id" : "drc_practice_4x4x20::@6890427a1f51a3e7e1df",
					"jsonFile" : "target-drc_practice_4x4x20-ffe687216ba93e92ee99.json",
					"name" : "drc_practice_4x4x20",
					"projectIndex" : 0
				},
				{
					"directoryIndex" : 0,
					"id" : "drc_practice_4x4x40::@6890427a1f51a3e7e1df",
					"jsonFile" : "target-drc_practice_4x4x40-2c7e583b16fea33fcbb7.json",
					"name" : "drc_practice_4x4x40",
					"projectIndex" : 0
				},
				{
					"directoryIndex" : 0,
					"id" : "drc_practice_angled_barrier_135::@6890427a1f51a3e7e1df",
					"jsonFile" : "target-drc_practice_angled_barrier_135-9adf4590a6e84e03335c.json",
					"name" : "drc_practice_angled_barrier_135",
					"projectIndex" : 0
				},
				{
					"directoryIndex" : 0,
					"id" : "drc_practice_angled_barrier_45::@6890427a1f51a3e7e1df",
					"jsonFile" : "target-drc_practice_angled_barrier_45-c397ebc326388420c2f7.json",
					"name" : "drc_practice_angled_barrier_45",
					"projectIndex" : 0
				},
				{
					"directoryIndex" : 0,
					"id" : "drc_practice_ball_valve::@6890427a1f51a3e7e1df",
					"jsonFile" : "target-drc_practice_ball_valve-777c8e48d0b384f4ffa9.json",
					"name" : "drc_practice_ball_valve",
					"projectIndex" : 0
				},
				{
					"directoryIndex" : 0,
					"id" : "drc_practice_ball_valve_wall::@6890427a1f51a3e7e1df",
					"jsonFile" : "target-drc_practice_ball_valve_wall-590225916c77f625238e.json",
					"name" : "drc_practice_ball_valve_wall",
					"projectIndex" : 0
				},
				{
					"directoryIndex" : 0,
					"id" : "drc_practice_base_4x8::@6890427a1f51a3e7e1df",
					"jsonFile" : "target-drc_practice_base_4x8-20ca35bb045857099bfa.json",
					"name" : "drc_practice_base_4x8",
					"projectIndex" : 0
				},
				{
					"directoryIndex" : 0,
					"id" : "drc_practice_block_wall::@6890427a1f51a3e7e1df",
					"jsonFile" : "target-drc_practice_block_wall-9b7d334ae131c0e66138.json",
					"name" : "drc_practice_block_wall",
					"projectIndex" : 0
				},
				{
					"directoryIndex" : 0,
					"id" : "drc_practice_blue_cylinder::@6890427a1f51a3e7e1df",
					"jsonFile" : "target-drc_practice_blue_cylinder-214c30efd2eb921a0913.json",
					"name" : "drc_practice_blue_cylinder",
					"projectIndex" : 0
				},
				{
					"directoryIndex" : 0,
					"id" : "drc_practice_door_4x8::@6890427a1f51a3e7e1df",
					"jsonFile" : "target-drc_practice_door_4x8-e54abab3585e8e41507a.json",
					"name" : "drc_practice_door_4x8",
					"projectIndex" : 0
				},
				{
					"directoryIndex" : 0,
					"id" : "drc_practice_hand_wheel_valve::@6890427a1f51a3e7e1df",
					"jsonFile" : "target-drc_practice_hand_wheel_valve-091c2e1d13bc07544bae.json",
					"name" : "drc_practice_hand_wheel_valve",
					"projectIndex" : 0
				},
				{
					"directoryIndex" : 0,
					"id" : "drc_practice_hand_wheel_valve_wall::@6890427a1f51a3e7e1df",
					"jsonFile" : "target-drc_practice_hand_wheel_valve_wall-2f12eb1dde7055f776fa.json",
					"name" : "drc_practice_hand_wheel_valve_wall",
					"projectIndex" : 0
				},
				{
					"directoryIndex" : 0,
					"id" : "drc_practice_handle_wheel_valve::@6890427a1f51a3e7e1df",
					"jsonFile" : "target-drc_practice_handle_wheel_valve-417f13f31ee3c6442e84.json",
					"name" : "drc_practice_handle_wheel_valve",
					"projectIndex" : 0
				},
				{
					"directoryIndex" : 0,
					"id" : "drc_practice_handle_wheel_valve_wall::@6890427a1f51a3e7e1df",
					"jsonFile" : "target-drc_practice_handle_wheel_valve_wall-ef677628c5ec3aac15a7.json",
					"name" : "drc_practice_handle_wheel_valve_wall",
					"projectIndex" : 0
				},
				{
					"directoryIndex" : 0,
					"id" : "drc_practice_hinged_door::@6890427a1f51a3e7e1df",
					"jsonFile" : "target-drc_practice_hinged_door-c6636ff41c52cc4cd78b.json",
					"name" : "drc_practice_hinged_door",
					"projectIndex" : 0
				},
				{
					"directoryIndex" : 0,
					"id" : "drc_practice_ladder::@6890427a1f51a3e7e1df",
					"jsonFile" : "target-drc_practice_ladder-072ae1abb39d84deded2.json",
					"name" : "drc_practice_ladder",
					"projectIndex" : 0
				},
				{
					"directoryIndex" : 0,
					"id" : "drc_practice_orange_jersey_barrier::@6890427a1f51a3e7e1df",
					"jsonFile" : "target-drc_practice_orange_jersey_barrier-6da119a13b6c6ab92d50.json",
					"name" : "drc_practice_orange_jersey_barrier",
					"projectIndex" : 0
				},
				{
					"directoryIndex" : 0,
					"id" : "drc_practice_truss::@6890427a1f51a3e7e1df",
					"jsonFile" : "target-drc_practice_truss-0044c8354f045b54a2e7.json",
					"name" : "drc_practice_truss",
					"projectIndex" : 0
				},
				{
					"directoryIndex" : 0,
					"id" : "drc_practice_valve_wall::@6890427a1f51a3e7e1df",
					"jsonFile" : "target-drc_practice_valve_wall-363395221328f7a3d952.json",
					"name" : "drc_practice_valve_wall",
					"projectIndex" : 0
				},
				{
					"directoryIndex" : 0,
					"id" : "drc_practice_weighted_door::@6890427a1f51a3e7e1df",
					"jsonFile" : "target-drc_practice_weighted_door-164b6a7498d7bde8a421.json",
					"name" : "drc_practice_weighted_door",
					"projectIndex" : 0
				},
				{
					"directoryIndex" : 0,
					"id" : "drc_practice_wheel_valve::@6890427a1f51a3e7e1df",
					"jsonFile" : "target-drc_practice_wheel_valve-eacb68ada4e7a0547505.json",
					"name" : "drc_practice_wheel_valve",
					"projectIndex" : 0
				},
				{
					"directoryIndex" : 0,
					"id" : "drc_practice_wheel_valve_large_wall::@6890427a1f51a3e7e1df",
					"jsonFile" : "target-drc_practice_wheel_valve_large_wall-c3dc8e9906b093c7ad7f.json",
					"name" : "drc_practice_wheel_valve_large_wall",
					"projectIndex" : 0
				},
				{
					"directoryIndex" : 0,
					"id" : "drc_practice_wheel_valve_wall::@6890427a1f51a3e7e1df",
					"jsonFile" : "target-drc_practice_wheel_valve_wall-41795d1f5fb8ffed7761.json",
					"name" : "drc_practice_wheel_valve_wall",
					"projectIndex" : 0
				},
				{
					"directoryIndex" : 0,
					"id" : "drc_practice_white_jersey_barrier::@6890427a1f51a3e7e1df",
					"jsonFile" : "target-drc_practice_white_jersey_barrier-b3ec82c212aeac4d5b28.json",
					"name" : "drc_practice_white_jersey_barrier",
					"projectIndex" : 0
				},
				{
					"directoryIndex" : 0,
					"id" : "drc_practice_wood_slats::@6890427a1f51a3e7e1df",
					"jsonFile" : "target-drc_practice_wood_slats-dc7aaa51cf24959facfa.json",
					"name" : "drc_practice_wood_slats",
					"projectIndex" : 0
				},
				{
					"directoryIndex" : 0,
					"id" : "drc_practice_yellow_parking_block::@6890427a1f51a3e7e1df",
					"jsonFile" : "target-drc_practice_yellow_parking_block-b6bcbebd2e4a6d052acc.json",
					"name" : "drc_practice_yellow_parking_block",
					"projectIndex" : 0
				},
				{
					"directoryIndex" : 0,
					"id" : "dumpster::@6890427a1f51a3e7e1df",
					"jsonFile" : "target-dumpster-b7035c2bafe3b6cf3944.json",
					"name" : "dumpster",
					"projectIndex" : 0
				},
				{
					"directoryIndex" : 0,
					"id" : "euro_pallet::@6890427a1f51a3e7e1df",
					"jsonFile" : "target-euro_pallet-1a4cada79ae06a62f945.json",
					"name" : "euro_pallet",
					"projectIndex" : 0
				},
				{
					"directoryIndex" : 0,
					"id" : "fast_food::@6890427a1f51a3e7e1df",
					"jsonFile" : "target-fast_food-84f9ab203c953b97f60c.json",
					"name" : "fast_food",
					"projectIndex" : 0
				},
				{
					"directoryIndex" : 0,
					"id" : "fire_hose_long::@6890427a1f51a3e7e1df",
					"jsonFile" : "target-fire_hose_long-adca1980ed9dc921fb2a.json",
					"name" : "fire_hose_long",
					"projectIndex" : 0
				},
				{
					"directoryIndex" : 0,
					"id" : "fire_hose_long_curled::@6890427a1f51a3e7e1df",
					"jsonFile" : "target-fire_hose_long_curled-76abbf742c616053b771.json",
					"name" : "fire_hose_long_curled",
					"projectIndex" : 0
				},
				{
					"directoryIndex" : 0,
					"id" : "fire_hydrant::@6890427a1f51a3e7e1df",
					"jsonFile" : "target-fire_hydrant-a8053fee574ec93cc7a4.json",
					"name" : "fire_hydrant",
					"projectIndex" : 0
				},
				{
					"directoryIndex" : 0,
					"id" : "fire_station::@6890427a1f51a3e7e1df",
					"jsonFile" : "target-fire_station-e40f8e65b57c95c88d26.json",
					"name" : "fire_station",
					"projectIndex" : 0
				},
				{
					"directoryIndex" : 0,
					"id" : "fire_truck::@6890427a1f51a3e7e1df",
					"jsonFile" : "target-fire_truck-59ec580fb54a2db342cd.json",
					"name" : "fire_truck",
					"projectIndex" : 0
				},
				{
					"directoryIndex" : 0,
					"id" : "first_2015_trash_can::@6890427a1f51a3e7e1df",
					"jsonFile" : "target-first_2015_trash_can-3ee15be8184a589079d6.json",
					"name" : "first_2015_trash_can",
					"projectIndex" : 0
				},
				{
					"directoryIndex" : 0,
					"id" : "follower_vehicle::@6890427a1f51a3e7e1df",
					"jsonFile" : "target-follower_vehicle-b420a00cd62c90453683.json",
					"name" : "follower_vehicle",
					"projectIndex" : 0
				},
				{
					"directoryIndex" : 0,
					"id" : "fountain::@6890427a1f51a3e7e1df",
					"jsonFile" : "target-fountain-dc3be89e754ed9009818.json",
					"name" : "fountain",
					"projectIndex" : 0
				},
				{
					"directoryIndex" : 0,
					"id" : "gas_station::@6890427a1f51a3e7e1df",
					"jsonFile" : "target-gas_station-ed88552c7fde3580a39d.json",
					"name" : "gas_station",
					"projectIndex" : 0
				},
				{
					"directoryIndex" : 0,
					"id" : "gasket_part::@6890427a1f51a3e7e1df",
					"jsonFile" : "target-gasket_part-66db103505a8a498ceba.json",
					"name" : "gasket_part",
					"projectIndex" : 0
				},
				{
					"directoryIndex" : 0,
					"id" : "gazebo::@6890427a1f51a3e7e1df",
					"jsonFile" : "target-gazebo-c67111f9c8d8829ce4b2.json",
					"name" : "gazebo",
					"projectIndex" : 0
				},
				{
					"directoryIndex" : 0,
					"id" : "gear_part::@6890427a1f51a3e7e1df",
					"jsonFile" : "target-gear_part-d1a61f3d40504064392a.json",
					"name" : "gear_part",
					"projectIndex" : 0
				},
				{
					"directoryIndex" : 0,
					"id" : "grey_tote::@6890427a1f51a3e7e1df",
					"jsonFile" : "target-grey_tote-e290b0aa20d47cfd6e9c.json",
					"name" : "grey_tote",
					"projectIndex" : 0
				},
				{
					"directoryIndex" : 0,
					"id" : "grey_wall::@6890427a1f51a3e7e1df",
					"jsonFile" : "target-grey_wall-b709d85fc2aca7763abc.json",
					"name" : "grey_wall",
					"projectIndex" : 0
				},
				{
					"directoryIndex" : 0,
					"id" : "grocery_store::@6890427a1f51a3e7e1df",
					"jsonFile" : "target-grocery_store-37ed82a806e2a777a4df.json",
					"name" : "grocery_store",
					"projectIndex" : 0
				},
				{
					"directoryIndex" : 0,
					"id" : "ground_plane::@6890427a1f51a3e7e1df",
					"jsonFile" : "target-ground_plane-0e1b62b927e3597fe701.json",
					"name" : "ground_plane",
					"projectIndex" : 0
				},
				{
					"directoryIndex" : 0,
					"id" : "hammer::@6890427a1f51a3e7e1df",
					"jsonFile" : "target-hammer-1cbb3933ba9cca70c628.json",
					"name" : "hammer",
					"projectIndex" : 0
				},
				{
					"directoryIndex" : 0,
					"id" : "hatchback::@6890427a1f51a3e7e1df",
					"jsonFile" : "target-hatchback-599b9d950022bb82b2a1.json",
					"name" : "hatchback",
					"projectIndex" : 0
				},
				{
					"directoryIndex" : 0,
					"id" : "hatchback_blue::@6890427a1f51a3e7e1df",
					"jsonFile" : "target-hatchback_blue-4899183530d1476caaa2.json",
					"name" : "hatchback_blue",
					"projectIndex" : 0
				},
				{
					"directoryIndex" : 0,
					"id" : "hatchback_red::@6890427a1f51a3e7e1df",
					"jsonFile" : "target-hatchback_red-74ca85237f58233c753f.json",
					"name" : "hatchback_red",
					"projectIndex" : 0
				},
				{
					"directoryIndex" : 0,
					"id" : "hinged_door::@6890427a1f51a3e7e1df",
					"jsonFile" : "target-hinged_door-d079de44a8d2cbad8709.json",
					"name" : "hinged_door",
					"projectIndex" : 0
				},
				{
					"directoryIndex" : 0,
					"id" : "hokuyo::@6890427a1f51a3e7e1df",
					"jsonFile" : "target-hokuyo-fe40c8465e5a71d68a6b.json",
					"name" : "hokuyo",
					"projectIndex" : 0
				},
				{
					"directoryIndex" : 0,
					"id" : "hoop_red::@6890427a1f51a3e7e1df",
					"jsonFile" : "target-hoop_red-90dbdf1baeb3c2e63fbc.json",
					"name" : "hoop_red",
					"projectIndex" : 0
				},
				{
					"directoryIndex" : 0,
					"id" : "house_1::@6890427a1f51a3e7e1df",
					"jsonFile" : "target-house_1-6faa0d304ffd91527d69.json",
					"name" : "house_1",
					"projectIndex" : 0
				},
				{
					"directoryIndex" : 0,
					"id" : "house_2::@6890427a1f51a3e7e1df",
					"jsonFile" : "target-house_2-566f76867dbe81773488.json",
					"name" : "house_2",
					"projectIndex" : 0
				},
				{
					"directoryIndex" : 0,
					"id" : "house_3::@6890427a1f51a3e7e1df",
					"jsonFile" : "target-house_3-62a629ee28d4e7fa3aa5.json",
					"name" : "house_3",
					"projectIndex" : 0
				},
				{
					"directoryIndex" : 0,
					"id" : "husky::@6890427a1f51a3e7e1df",
					"jsonFile" : "target-husky-432ee43bd2771c0d585f.json",
					"name" : "husky",
					"projectIndex" : 0
				},
				{
					"directoryIndex" : 0,
					"id" : "intel_realsense_r200::@6890427a1f51a3e7e1df",
					"jsonFile" : "target-intel_realsense_r200-033b184f9fc0feb60c27.json",
					"name" : "intel_realsense_r200",
					"projectIndex" : 0
				},
				{
					"directoryIndex" : 0,
					"id" : "iris_with_standoffs_demo::@6890427a1f51a3e7e1df",
					"jsonFile" : "target-iris_with_standoffs_demo-06977a32a83d65a799d4.json",
					"name" : "iris_with_standoffs_demo",
					"projectIndex" : 0
				},
				{
					"directoryIndex" : 0,
					"id" : "iss_half::@6890427a1f51a3e7e1df",
					"jsonFile" : "target-iss_half-a45ac9fce19a7da98df1.json",
					"name" : "iss_half",
					"projectIndex" : 0
				},
				{
					"directoryIndex" : 0,
					"id" : "jersey_barrier::@6890427a1f51a3e7e1df",
					"jsonFile" : "target-jersey_barrier-9edb5e4967c8ff1ef1f7.json",
					"name" : "jersey_barrier",
					"projectIndex" : 0
				},
				{
					"directoryIndex" : 0,
					"id" : "kinect::@6890427a1f51a3e7e1df",
					"jsonFile" : "target-kinect-142b274cae2dc42e5fb8.json",
					"name" : "kinect",
					"projectIndex" : 0
				},
				{
					"directoryIndex" : 0,
					"id" : "ladder_60deg_0rails::@6890427a1f51a3e7e1df",
					"jsonFile" : "target-ladder_60deg_0rails-3ce29e7d090d8cf1a882.json",
					"name" : "ladder_60deg_0rails",
					"projectIndex" : 0
				},
				{
					"directoryIndex" : 0,
					"id" : "ladder_60deg_1rails::@6890427a1f51a3e7e1df",
					"jsonFile" : "target-ladder_60deg_1rails-91424d793711d9122e0e.json",
					"name" : "ladder_60deg_1rails",
					"projectIndex" : 0
				},
				{
					"directoryIndex" : 0,
					"id" : "ladder_60deg_2rails::@6890427a1f51a3e7e1df",
					"jsonFile" : "target-ladder_60deg_2rails-b33bfd7946fdd1f8762f.json",
					"name" : "ladder_60deg_2rails",
					"projectIndex" : 0
				},
				{
					"directoryIndex" : 0,
					"id" : "ladder_75deg_0rails::@6890427a1f51a3e7e1df",
					"jsonFile" : "target-ladder_75deg_0rails-13708cae4ac92eea85d0.json",
					"name" : "ladder_75deg_0rails",
					"projectIndex" : 0
				},
				{
					"directoryIndex" : 0,
					"id" : "ladder_75deg_1rails::@6890427a1f51a3e7e1df",
					"jsonFile" : "target-ladder_75deg_1rails-31486372574edfd7ee71.json",
					"name" : "ladder_75deg_1rails",
					"projectIndex" : 0
				},
				{
					"directoryIndex" : 0,
					"id" : "ladder_75deg_2rails::@6890427a1f51a3e7e1df",
					"jsonFile" : "target-ladder_75deg_2rails-7e5077853f86849ef17a.json",
					"name" : "ladder_75deg_2rails",
					"projectIndex" : 0
				},
				{
					"directoryIndex" : 0,
					"id" : "lamp_post::@6890427a1f51a3e7e1df",
					"jsonFile" : "target-lamp_post-61f5c8cc8aa879a8e88e.json",
					"name" : "lamp_post",
					"projectIndex" : 0
				},
				{
					"directoryIndex" : 0,
					"id" : "law_office::@6890427a1f51a3e7e1df",
					"jsonFile" : "target-law_office-708e60d768cc0c85c262.json",
					"name" : "law_office",
					"projectIndex" : 0
				},
				{
					"directoryIndex" : 0,
					"id" : "lunar_tranquillitatis_pit::@6890427a1f51a3e7e1df",
					"jsonFile" : "target-lunar_tranquillitatis_pit-65232981363a6c20f5ba.json",
					"name" : "lunar_tranquillitatis_pit",
					"projectIndex" : 0
				},
				{
					"directoryIndex" : 0,
					"id" : "mailbox::@6890427a1f51a3e7e1df",
					"jsonFile" : "target-mailbox-7bf7d464ecf670a1f4dc.json",
					"name" : "mailbox",
					"projectIndex" : 0
				},
				{
					"directoryIndex" : 0,
					"id" : "marble_1_5cm::@6890427a1f51a3e7e1df",
					"jsonFile" : "target-marble_1_5cm-cd3c283ba0b7acfcb0a9.json",
					"name" : "marble_1_5cm",
					"projectIndex" : 0
				},
				{
					"directoryIndex" : 0,
					"id" : "mars_rover::@6890427a1f51a3e7e1df",
					"jsonFile" : "target-mars_rover-92445366f65dda91503c.json",
					"name" : "mars_rover",
					"projectIndex" : 0
				},
				{
					"directoryIndex" : 0,
					"id" : "mass_on_rails::@6890427a1f51a3e7e1df",
					"jsonFile" : "target-mass_on_rails-6dc833ce08b9d23cf30d.json",
					"name" : "mass_on_rails",
					"projectIndex" : 0
				},
				{
					"directoryIndex" : 0,
					"id" : "metal_peg::@6890427a1f51a3e7e1df",
					"jsonFile" : "target-metal_peg-eef90e271a6002a39db0.json",
					"name" : "metal_peg",
					"projectIndex" : 0
				},
				{
					"directoryIndex" : 0,
					"id" : "metal_peg_board::@6890427a1f51a3e7e1df",
					"jsonFile" : "target-metal_peg_board-7a3e79325605690e8077.json",
					"name" : "metal_peg_board",
					"projectIndex" : 0
				},
				{
					"directoryIndex" : 0,
					"id" : "monkey_wrench::@6890427a1f51a3e7e1df",
					"jsonFile" : "target-monkey_wrench-46b5ab70f2c38b943789.json",
					"name" : "monkey_wrench",
					"projectIndex" : 0
				},
				{
					"directoryIndex" : 0,
					"id" : "mpl_right_arm::@6890427a1f51a3e7e1df",
					"jsonFile" : "target-mpl_right_arm-8831d7f149b4c8bbd9bb.json",
					"name" : "mpl_right_arm",
					"projectIndex" : 0
				},
				{
					"directoryIndex" : 0,
					"id" : "mpl_right_forearm::@6890427a1f51a3e7e1df",
					"jsonFile" : "target-mpl_right_forearm-a6f1ae8e79c0ea72b9d1.json",
					"name" : "mpl_right_forearm",
					"projectIndex" : 0
				},
				{
					"directoryIndex" : 0,
					"id" : "mud_box::@6890427a1f51a3e7e1df",
					"jsonFile" : "target-mud_box-22d134bef60afbe00597.json",
					"name" : "mud_box",
					"projectIndex" : 0
				},
				{
					"directoryIndex" : 0,
					"id" : "nist_elevated_floor_120::@6890427a1f51a3e7e1df",
					"jsonFile" : "target-nist_elevated_floor_120-95296217aec88923af54.json",
					"name" : "nist_elevated_floor_120",
					"projectIndex" : 0
				},
				{
					"directoryIndex" : 0,
					"id" : "nist_fiducial_barrel::@6890427a1f51a3e7e1df",
					"jsonFile" : "target-nist_fiducial_barrel-d69867451d81013f9caf.json",
					"name" : "nist_fiducial_barrel",
					"projectIndex" : 0
				},
				{
					"directoryIndex" : 0,
					"id" : "nist_maze_wall_120::@6890427a1f51a3e7e1df",
					"jsonFile" : "target-nist_maze_wall_120-d0b353c14068591a1744.json",
					"name" : "nist_maze_wall_120",
					"projectIndex" : 0
				},
				{
					"directoryIndex" : 0,
					"id" : "nist_maze_wall_240::@6890427a1f51a3e7e1df",
					"jsonFile" : "target-nist_maze_wall_240-87eb09c64765f7606460.json",
					"name" : "nist_maze_wall_240",
					"projectIndex" : 0
				},
				{
					"directoryIndex" : 0,
					"id" : "nist_maze_wall_triple_holes_120::@6890427a1f51a3e7e1df",
					"jsonFile" : "target-nist_maze_wall_triple_holes_120-03aa0b490fbaebab457e.json",
					"name" : "nist_maze_wall_triple_holes_120",
					"projectIndex" : 0
				},
				{
					"directoryIndex" : 0,
					"id" : "nist_simple_ramp_120::@6890427a1f51a3e7e1df",
					"jsonFile" : "target-nist_simple_ramp_120-6de0acd77ebff1b3b43f.json",
					"name" : "nist_simple_ramp_120",
					"projectIndex" : 0
				},
				{
					"directoryIndex" : 0,
					"id" : "nist_stairs_120::@6890427a1f51a3e7e1df",
					"jsonFile" : "target-nist_stairs_120-d579d4b20d7b642c893a.json",
					"name" : "nist_stairs_120",
					"projectIndex" : 0
				},
				{
					"directoryIndex" : 0,
					"id" : "number1::@6890427a1f51a3e7e1df",
					"jsonFile" : "target-number1-86b8c60587366cd19cb0.json",
					"name" : "number1",
					"projectIndex" : 0
				},
				{
					"directoryIndex" : 0,
					"id" : "number2::@6890427a1f51a3e7e1df",
					"jsonFile" : "target-number2-81ebd0bda96a9883ac6c.json",
					"name" : "number2",
					"projectIndex" : 0
				},
				{
					"directoryIndex" : 0,
					"id" : "number3::@6890427a1f51a3e7e1df",
					"jsonFile" : "target-number3-9663035da7821e447979.json",
					"name" : "number3",
					"projectIndex" : 0
				},
				{
					"directoryIndex" : 0,
					"id" : "number4::@6890427a1f51a3e7e1df",
					"jsonFile" : "target-number4-eb2dc7f1f501919c9f3a.json",
					"name" : "number4",
					"projectIndex" : 0
				},
				{
					"directoryIndex" : 0,
					"id" : "number5::@6890427a1f51a3e7e1df",
					"jsonFile" : "target-number5-79ff69dc8dc235df7690.json",
					"name" : "number5",
					"projectIndex" : 0
				},
				{
					"directoryIndex" : 0,
					"id" : "number6::@6890427a1f51a3e7e1df",
					"jsonFile" : "target-number6-81fcc37aa8d5d04fffb0.json",
					"name" : "number6",
					"projectIndex" : 0
				},
				{
					"directoryIndex" : 0,
					"id" : "number7::@6890427a1f51a3e7e1df",
					"jsonFile" : "target-number7-a39054c05bd79430f78f.json",
					"name" : "number7",
					"projectIndex" : 0
				},
				{
					"directoryIndex" : 0,
					"id" : "number8::@6890427a1f51a3e7e1df",
					"jsonFile" : "target-number8-e8bca4d27466b4fe9366.json",
					"name" : "number8",
					"projectIndex" : 0
				},
				{
					"directoryIndex" : 0,
					"id" : "number9::@6890427a1f51a3e7e1df",
					"jsonFile" : "target-number9-89451e7c0740a6e9643a.json",
					"name" : "number9",
					"projectIndex" : 0
				},
				{
					"directoryIndex" : 0,
					"id" : "oak_tree::@6890427a1f51a3e7e1df",
					"jsonFile" : "target-oak_tree-1005592ec971140d99bc.json",
					"name" : "oak_tree",
					"projectIndex" : 0
				},
				{
					"directoryIndex" : 0,
					"id" : "office_building::@6890427a1f51a3e7e1df",
					"jsonFile" : "target-office_building-8bf612a3233a9d112983.json",
					"name" : "office_building",
					"projectIndex" : 0
				},
				{
					"directoryIndex" : 0,
					"id" : "orbbec_astra_camera::@6890427a1f51a3e7e1df",
					"jsonFile" : "target-orbbec_astra_camera-30387af696e84119e4ae.json",
					"name" : "orbbec_astra_camera",
					"projectIndex" : 0
				},
				{
					"directoryIndex" : 0,
					"id" : "osrf_elevator::@6890427a1f51a3e7e1df",
					"jsonFile" : "target-osrf_elevator-ef7e734b1082965d105d.json",
					"name" : "osrf_elevator",
					"projectIndex" : 0
				},
				{
					"directoryIndex" : 0,
					"id" : "osrf_first_office::@6890427a1f51a3e7e1df",
					"jsonFile" : "target-osrf_first_office-2b7b1a96942287ae7f27.json",
					"name" : "osrf_first_office",
					"projectIndex" : 0
				},
				{
					"directoryIndex" : 0,
					"id" : "parking_garage::@6890427a1f51a3e7e1df",
					"jsonFile" : "target-parking_garage-306ed2b37da8cc56b589.json",
					"name" : "parking_garage",
					"projectIndex" : 0
				},
				{
					"directoryIndex" : 0,
					"id" : "parrot_bebop_2::@6890427a1f51a3e7e1df",
					"jsonFile" : "target-parrot_bebop_2-be0e105b548ec52e51df.json",
					"name" : "parrot_bebop_2",
					"projectIndex" : 0
				},
				{
					"directoryIndex" : 0,
					"id" : "person_standing::@6890427a1f51a3e7e1df",
					"jsonFile" : "target-person_standing-69c01f7e34499153779e.json",
					"name" : "person_standing",
					"projectIndex" : 0
				},
				{
					"directoryIndex" : 0,
					"id" : "person_walking::@6890427a1f51a3e7e1df",
					"jsonFile" : "target-person_walking-c5d9d14efb37a471b627.json",
					"name" : "person_walking",
					"projectIndex" : 0
				},
				{
					"directoryIndex" : 0,
					"id" : "pickup::@6890427a1f51a3e7e1df",
					"jsonFile" : "target-pickup-3ac8f6567f7d5039bc16.json",
					"name" : "pickup",
					"projectIndex" : 0
				},
				{
					"directoryIndex" : 0,
					"id" : "pier::@6890427a1f51a3e7e1df",
					"jsonFile" : "target-pier-0ca48c87ff935f58bab2.json",
					"name" : "pier",
					"projectIndex" : 0
				},
				{
					"directoryIndex" : 0,
					"id" : "pine_tree::@6890427a1f51a3e7e1df",
					"jsonFile" : "target-pine_tree-568da35a5b94e07fd070.json",
					"name" : "pine_tree",
					"projectIndex" : 0
				},
				{
					"directoryIndex" : 0,
					"id" : "pioneer2dx::@6890427a1f51a3e7e1df",
					"jsonFile" : "target-pioneer2dx-1d22b29615869bc536ae.json",
					"name" : "pioneer2dx",
					"projectIndex" : 0
				},
				{
					"directoryIndex" : 0,
					"id" : "pioneer3at::@6890427a1f51a3e7e1df",
					"jsonFile" : "target-pioneer3at-a3338a377f7a44a2980d.json",
					"name" : "pioneer3at",
					"projectIndex" : 0
				},
				{
					"directoryIndex" : 0,
					"id" : "piston_rod_part::@6890427a1f51a3e7e1df",
					"jsonFile" : "target-piston_rod_part-933d86118edb92a01ff6.json",
					"name" : "piston_rod_part",
					"projectIndex" : 0
				},
				{
					"directoryIndex" : 0,
					"id" : "plastic_cup::@6890427a1f51a3e7e1df",
					"jsonFile" : "target-plastic_cup-7d8b4fd749e03a47b728.json",
					"name" : "plastic_cup",
					"projectIndex" : 0
				},
				{
					"directoryIndex" : 0,
					"id" : "playground::@6890427a1f51a3e7e1df",
					"jsonFile" : "target-playground-8c8fc50fd967b53ecc27.json",
					"name" : "playground",
					"projectIndex" : 0
				},
				{
					"directoryIndex" : 0,
					"id" : "polaris_ranger_ev::@6890427a1f51a3e7e1df",
					"jsonFile" : "target-polaris_ranger_ev-b4cd6b2db970f2a050fb.json",
					"name" : "polaris_ranger_ev",
					"projectIndex" : 0
				},
				{
					"directoryIndex" : 0,
					"id" : "polaris_ranger_xp900::@6890427a1f51a3e7e1df",
					"jsonFile" : "target-polaris_ranger_xp900-47719fd15be00baeb213.json",
					"name" : "polaris_ranger_xp900",
					"projectIndex" : 0
				},
				{
					"directoryIndex" : 0,
					"id" : "polaris_ranger_xp900_no_roll_cage::@6890427a1f51a3e7e1df",
					"jsonFile" : "target-polaris_ranger_xp900_no_roll_cage-b85f39f431e0f0650e70.json",
					"name" : "polaris_ranger_xp900_no_roll_cage",
					"projectIndex" : 0
				},
				{
					"directoryIndex" : 0,
					"id" : "police_station::@6890427a1f51a3e7e1df",
					"jsonFile" : "target-police_station-815c417a6607ef7269c8.json",
					"name" : "police_station",
					"projectIndex" : 0
				},
				{
					"directoryIndex" : 0,
					"id" : "post_office::@6890427a1f51a3e7e1df",
					"jsonFile" : "target-post_office-f0a8ea07e08c1c3ff1d3.json",
					"name" : "post_office",
					"projectIndex" : 0
				},
				{
					"directoryIndex" : 0,
					"id" : "postbox::@6890427a1f51a3e7e1df",
					"jsonFile" : "target-postbox-c350388d78a5b9bd60c0.json",
					"name" : "postbox",
					"projectIndex" : 0
				},
				{
					"directoryIndex" : 0,
					"id" : "powerplant::@6890427a1f51a3e7e1df",
					"jsonFile" : "target-powerplant-1e96f852421836d7697a.json",
					"name" : "powerplant",
					"projectIndex" : 0
				},
				{
					"directoryIndex" : 0,
					"id" : "pr2::@6890427a1f51a3e7e1df",
					"jsonFile" : "target-pr2-615e3ed8fab0484d69b0.json",
					"name" : "pr2",
					"projectIndex" : 0
				},
				{
					"directoryIndex" : 0,
					"id" : "pr2_gripper::@6890427a1f51a3e7e1df",
					"jsonFile" : "target-pr2_gripper-3950a117858fc0ca9c4e.json",
					"name" : "pr2_gripper",
					"projectIndex" : 0
				},
				{
					"directoryIndex" : 0,
					"id" : "prius_hybrid::@6890427a1f51a3e7e1df",
					"jsonFile" : "target-prius_hybrid-26c169470f59084ebf9a.json",
					"name" : "prius_hybrid",
					"projectIndex" : 0
				},
				{
					"directoryIndex" : 0,
					"id" : "prius_hybrid_sensors::@6890427a1f51a3e7e1df",
					"jsonFile" : "target-prius_hybrid_sensors-b2a84bd68959d8961e86.json",
					"name" : "prius_hybrid_sensors",
					"projectIndex" : 0
				},
				{
					"directoryIndex" : 0,
					"id" : "pulley_part::@6890427a1f51a3e7e1df",
					"jsonFile" : "target-pulley_part-42b65bfb1854245fd9f1.json",
					"name" : "pulley_part",
					"projectIndex" : 0
				},
				{
					"directoryIndex" : 0,
					"id" : "quadrotor::@6890427a1f51a3e7e1df",
					"jsonFile" : "target-quadrotor-fdc3e35b91365bad8fd3.json",
					"name" : "quadrotor",
					"projectIndex" : 0
				},
				{
					"directoryIndex" : 0,
					"id" : "r2_description::@6890427a1f51a3e7e1df",
					"jsonFile" : "target-r2_description-a790057a2139d6f22e59.json",
					"name" : "r2_description",
					"projectIndex" : 0
				},
				{
					"directoryIndex" : 0,
					"id" : "radio_tower::@6890427a1f51a3e7e1df",
					"jsonFile" : "target-radio_tower-0aaefaead21429984dd6.json",
					"name" : "radio_tower",
					"projectIndex" : 0
				},
				{
					"directoryIndex" : 0,
					"id" : "ragdoll::@6890427a1f51a3e7e1df",
					"jsonFile" : "target-ragdoll-12b715fb93c2f9110780.json",
					"name" : "ragdoll",
					"projectIndex" : 0
				},
				{
					"directoryIndex" : 0,
					"id" : "reactor::@6890427a1f51a3e7e1df",
					"jsonFile" : "target-reactor-bb0241fb9b29544250be.json",
					"name" : "reactor",
					"projectIndex" : 0
				},
				{
					"directoryIndex" : 0,
					"id" : "region_event_box::@6890427a1f51a3e7e1df",
					"jsonFile" : "target-region_event_box-12fbffd168abee993fed.json",
					"name" : "region_event_box",
					"projectIndex" : 0
				},
				{
					"directoryIndex" : 0,
					"id" : "robocup09_spl_field::@6890427a1f51a3e7e1df",
					"jsonFile" : "target-robocup09_spl_field-c703e62c74bfc8afda29.json",
					"name" : "robocup09_spl_field",
					"projectIndex" : 0
				},
				{
					"directoryIndex" : 0,
					"id" : "robocup14_spl_field::@6890427a1f51a3e7e1df",
					"jsonFile" : "target-robocup14_spl_field-73f4c8b17064d58e852a.json",
					"name" : "robocup14_spl_field",
					"projectIndex" : 0
				},
				{
					"directoryIndex" : 0,
					"id" : "robocup14_spl_goal::@6890427a1f51a3e7e1df",
					"jsonFile" : "target-robocup14_spl_goal-2c9eecc14c84c01e5049.json",
					"name" : "robocup14_spl_goal",
					"projectIndex" : 0
				},
				{
					"directoryIndex" : 0,
					"id" : "robocup_3Dsim_ball::@6890427a1f51a3e7e1df",
					"jsonFile" : "target-robocup_3Dsim_ball-7d0b4f5b0043d5ef4989.json",
					"name" : "robocup_3Dsim_ball",
					"projectIndex" : 0
				},
				{
					"directoryIndex" : 0,
					"id" : "robocup_3Dsim_field::@6890427a1f51a3e7e1df",
					"jsonFile" : "target-robocup_3Dsim_field-bad7b69254bde18950ff.json",
					"name" : "robocup_3Dsim_field",
					"projectIndex" : 0
				},
				{
					"directoryIndex" : 0,
					"id" : "robocup_3Dsim_goal::@6890427a1f51a3e7e1df",
					"jsonFile" : "target-robocup_3Dsim_goal-c61dc480ff6ca5147c9d.json",
					"name" : "robocup_3Dsim_goal",
					"projectIndex" : 0
				},
				{
					"directoryIndex" : 0,
					"id" : "robocup_spl_ball::@6890427a1f51a3e7e1df",
					"jsonFile" : "target-robocup_spl_ball-ca9ea6c5a32fab8a2f18.json",
					"name" : "robocup_spl_ball",
					"projectIndex" : 0
				},
				{
					"directoryIndex" : 0,
					"id" : "robonaut::@6890427a1f51a3e7e1df",
					"jsonFile" : "target-robonaut-2d8f938ed7b97bf00dfc.json",
					"name" : "robonaut",
					"projectIndex" : 0
				},
				{
					"directoryIndex" : 0,
					"id" : "round_tin_base::@6890427a1f51a3e7e1df",
					"jsonFile" : "target-round_tin_base-f0b74f1e3337a819f320.json",
					"name" : "round_tin_base",
					"projectIndex" : 0
				},
				{
					"directoryIndex" : 0,
					"id" : "round_tin_top::@6890427a1f51a3e7e1df",
					"jsonFile" : "target-round_tin_top-e79fb2fda9ee988129cd.json",
					"name" : "round_tin_top",
					"projectIndex" : 0
				},
				{
					"directoryIndex" : 0,
					"id" : "salon::@6890427a1f51a3e7e1df",
					"jsonFile" : "target-salon-0ede9c66270171557c9e.json",
					"name" : "salon",
					"projectIndex" : 0
				},
				{
					"directoryIndex" : 0,
					"id" : "saucepan::@6890427a1f51a3e7e1df",
					"jsonFile" : "target-saucepan-ddc4d375d3c478ffce03.json",
					"name" : "saucepan",
					"projectIndex" : 0
				},
				{
					"directoryIndex" : 0,
					"id" : "scanse_sweep::@6890427a1f51a3e7e1df",
					"jsonFile" : "target-scanse_sweep-18f74c9af8d72167f0c2.json",
					"name" : "scanse_sweep",
					"projectIndex" : 0
				},
				{
					"directoryIndex" : 0,
					"id" : "school::@6890427a1f51a3e7e1df",
					"jsonFile" : "target-school-b7aed2f26b8da1a43a06.json",
					"name" : "school",
					"projectIndex" : 0
				},
				{
					"directoryIndex" : 0,
					"id" : "simple_arm::@6890427a1f51a3e7e1df",
					"jsonFile" : "target-simple_arm-21c520ca78800724bd34.json",
					"name" : "simple_arm",
					"projectIndex" : 0
				},
				{
					"directoryIndex" : 0,
					"id" : "simple_arm_gripper::@6890427a1f51a3e7e1df",
					"jsonFile" : "target-simple_arm_gripper-987a23edfff15492933f.json",
					"name" : "simple_arm_gripper",
					"projectIndex" : 0
				},
				{
					"directoryIndex" : 0,
					"id" : "simple_gripper::@6890427a1f51a3e7e1df",
					"jsonFile" : "target-simple_gripper-a05039b19ee03a2e3dc2.json",
					"name" : "simple_gripper",
					"projectIndex" : 0
				},
				{
					"directoryIndex" : 0,
					"id" : "spectrum_plane::@6890427a1f51a3e7e1df",
					"jsonFile" : "target-spectrum_plane-bd78c43348dbad30eb1b.json",
					"name" : "spectrum_plane",
					"projectIndex" : 0
				},
				{
					"directoryIndex" : 0,
					"id" : "speed_limit_sign::@6890427a1f51a3e7e1df",
					"jsonFile" : "target-speed_limit_sign-d22574c0a609c378666c.json",
					"name" : "speed_limit_sign",
					"projectIndex" : 0
				},
				{
					"directoryIndex" : 0,
					"id" : "src_doorway::@6890427a1f51a3e7e1df",
					"jsonFile" : "target-src_doorway-282e31ed5a36a93f7519.json",
					"name" : "src_doorway",
					"projectIndex" : 0
				},
				{
					"directoryIndex" : 0,
					"id" : "standpipe::@6890427a1f51a3e7e1df",
					"jsonFile" : "target-standpipe-62a6e54da7abe13ee664.json",
					"name" : "standpipe",
					"projectIndex" : 0
				},
				{
					"directoryIndex" : 0,
					"id" : "starting_pen::@6890427a1f51a3e7e1df",
					"jsonFile" : "target-starting_pen-962eb26d558bab4c4287.json",
					"name" : "starting_pen",
					"projectIndex" : 0
				},
				{
					"directoryIndex" : 0,
					"id" : "stereo_camera::@6890427a1f51a3e7e1df",
					"jsonFile" : "target-stereo_camera-fd1c47fe1644d23ef88c.json",
					"name" : "stereo_camera",
					"projectIndex" : 0
				},
				{
					"directoryIndex" : 0,
					"id" : "stone_10_2_5_1cm::@6890427a1f51a3e7e1df",
					"jsonFile" : "target-stone_10_2_5_1cm-be239b78f58522d1642d.json",
					"name" : "stone_10_2_5_1cm",
					"projectIndex" : 0
				},
				{
					"directoryIndex" : 0,
					"id" : "stop_light::@6890427a1f51a3e7e1df",
					"jsonFile" : "target-stop_light-f7882e02c23a8acfd942.json",
					"name" : "stop_light",
					"projectIndex" : 0
				},
				{
					"directoryIndex" : 0,
					"id" : "stop_light_post::@6890427a1f51a3e7e1df",
					"jsonFile" : "target-stop_light_post-64f91fd43c53630251cc.json",
					"name" : "stop_light_post",
					"projectIndex" : 0
				},
				{
					"directoryIndex" : 0,
					"id" : "stop_sign::@6890427a1f51a3e7e1df",
					"jsonFile" : "target-stop_sign-c84d627c42dc202a1c9e.json",
					"name" : "stop_sign",
					"projectIndex" : 0
				},
				{
					"directoryIndex" : 0,
					"id" : "submarine::@6890427a1f51a3e7e1df",
					"jsonFile" : "target-submarine-bf9ed399da32ab5c87c9.json",
					"name" : "submarine",
					"projectIndex" : 0
				},
				{
					"directoryIndex" : 0,
					"id" : "submarine_buoyant::@6890427a1f51a3e7e1df",
					"jsonFile" : "target-submarine_buoyant-7aac797c9a6ff2c00223.json",
					"name" : "submarine_buoyant",
					"projectIndex" : 0
				},
				{
					"directoryIndex" : 0,
					"id" : "submarine_sinking::@6890427a1f51a3e7e1df",
					"jsonFile" : "target-submarine_sinking-3ad8e97f0ef25042445c.json",
					"name" : "submarine_sinking",
					"projectIndex" : 0
				},
				{
					"directoryIndex" : 0,
					"id" : "sun::@6890427a1f51a3e7e1df",
					"jsonFile" : "target-sun-73848479137c01f1f1a9.json",
					"name" : "sun",
					"projectIndex" : 0
				},
				{
					"directoryIndex" : 0,
					"id" : "suv::@6890427a1f51a3e7e1df",
					"jsonFile" : "target-suv-521a378cfe2bd39e31e2.json",
					"name" : "suv",
					"projectIndex" : 0
				},
				{
					"directoryIndex" : 0,
					"id" : "t_brace_part::@6890427a1f51a3e7e1df",
					"jsonFile" : "target-t_brace_part-a716142eef677a5277d8.json",
					"name" : "t_brace_part",
					"projectIndex" : 0
				},
				{
					"directoryIndex" : 0,
					"id" : "table::@6890427a1f51a3e7e1df",
					"jsonFile" : "target-table-58962255e91b9f5863e4.json",
					"name" : "table",
					"projectIndex" : 0
				},
				{
					"directoryIndex" : 0,
					"id" : "table_marble::@6890427a1f51a3e7e1df",
					"jsonFile" : "target-table_marble-c11431485c56bdbacf99.json",
					"name" : "table_marble",
					"projectIndex" : 0
				},
				{
					"directoryIndex" : 0,
					"id" : "telephone_pole::@6890427a1f51a3e7e1df",
					"jsonFile" : "target-telephone_pole-601a35815019fa7ab258.json",
					"name" : "telephone_pole",
					"projectIndex" : 0
				},
				{
					"directoryIndex" : 0,
					"id" : "textured_shapes::@6890427a1f51a3e7e1df",
					"jsonFile" : "target-textured_shapes-c4560e343fa438f061d0.json",
					"name" : "textured_shapes",
					"projectIndex" : 0
				},
				{
					"directoryIndex" : 0,
					"id" : "thrift_shop::@6890427a1f51a3e7e1df",
					"jsonFile" : "target-thrift_shop-51b8d936af96c6acff88.json",
					"name" : "thrift_shop",
					"projectIndex" : 0
				},
				{
					"directoryIndex" : 0,
					"id" : "tower_crane::@6890427a1f51a3e7e1df",
					"jsonFile" : "target-tower_crane-5311a4f65f92181ee4fe.json",
					"name" : "tower_crane",
					"projectIndex" : 0
				},
				{
					"directoryIndex" : 0,
					"id" : "trisphere_cycle::@6890427a1f51a3e7e1df",
					"jsonFile" : "target-trisphere_cycle-5fd9ba40d61384dc1b9e.json",
					"name" : "trisphere_cycle",
					"projectIndex" : 0
				},
				{
					"directoryIndex" : 0,
					"id" : "truss_bridge::@6890427a1f51a3e7e1df",
					"jsonFile" : "target-truss_bridge-6369fc2188f552ddddfd.json",
					"name" : "truss_bridge",
					"projectIndex" : 0
				},
				{
					"directoryIndex" : 0,
					"id" : "tube_2_25cm::@6890427a1f51a3e7e1df",
					"jsonFile" : "target-tube_2_25cm-949d7e68618b2847f7d5.json",
					"name" : "tube_2_25cm",
					"projectIndex" : 0
				},
				{
					"directoryIndex" : 0,
					"id" : "tube_9_5mm::@6890427a1f51a3e7e1df",
					"jsonFile" : "target-tube_9_5mm-23265154c35d6b31c2ec.json",
					"name" : "tube_9_5mm",
					"projectIndex" : 0
				},
				{
					"directoryIndex" : 0,
					"id" : "turtlebot::@6890427a1f51a3e7e1df",
					"jsonFile" : "target-turtlebot-76b01bd96199ebccf318.json",
					"name" : "turtlebot",
					"projectIndex" : 0
				},
				{
					"directoryIndex" : 0,
					"id" : "u_joint_part::@6890427a1f51a3e7e1df",
					"jsonFile" : "target-u_joint_part-0cbf052ced12eba02638.json",
					"name" : "u_joint_part",
					"projectIndex" : 0
				},
				{
					"directoryIndex" : 0,
					"id" : "ur10::@6890427a1f51a3e7e1df",
					"jsonFile" : "target-ur10-7b565dfd0d33d81ca318.json",
					"name" : "ur10",
					"projectIndex" : 0
				},
				{
					"directoryIndex" : 0,
					"id" : "utility_cart::@6890427a1f51a3e7e1df",
					"jsonFile" : "target-utility_cart-b1776f3c102ed1d1d0c6.json",
					"name" : "utility_cart",
					"projectIndex" : 0
				},
				{
					"directoryIndex" : 0,
					"id" : "velodyne_hdl32::@6890427a1f51a3e7e1df",
					"jsonFile" : "target-velodyne_hdl32-b97638e1aec93d565a6b.json",
					"name" : "velodyne_hdl32",
					"projectIndex" : 0
				},
				{
					"directoryIndex" : 0,
					"id" : "vrc_driving_terrain::@6890427a1f51a3e7e1df",
					"jsonFile" : "target-vrc_driving_terrain-34f0f770874870de1845.json",
					"name" : "vrc_driving_terrain",
					"projectIndex" : 0
				},
				{
					"directoryIndex" : 0,
					"id" : "walkway_metal_45::@6890427a1f51a3e7e1df",
					"jsonFile" : "target-walkway_metal_45-42793d109acb53f1b258.json",
					"name" : "walkway_metal_45",
					"projectIndex" : 0
				},
				{
					"directoryIndex" : 0,
					"id" : "walkway_metal_90::@6890427a1f51a3e7e1df",
					"jsonFile" : "target-walkway_metal_90-c7717f449ec3e643e193.json",
					"name" : "walkway_metal_90",
					"projectIndex" : 0
				},
				{
					"directoryIndex" : 0,
					"id" : "walkway_metal_straight::@6890427a1f51a3e7e1df",
					"jsonFile" : "target-walkway_metal_straight-4ab577208be90a226c4e.json",
					"name" : "walkway_metal_straight",
					"projectIndex" : 0
				},
				{
					"directoryIndex" : 0,
					"id" : "warehouse_robot::@6890427a1f51a3e7e1df",
					"jsonFile" : "target-warehouse_robot-9b3cae1c45874fc2fd08.json",
					"name" : "warehouse_robot",
					"projectIndex" : 0
				},
				{
					"directoryIndex" : 0,
					"id" : "washer::@6890427a1f51a3e7e1df",
					"jsonFile" : "target-washer-b9b05ffe9c7ae0aa8da0.json",
					"name" : "washer",
					"projectIndex" : 0
				},
				{
					"directoryIndex" : 0,
					"id" : "water_tower::@6890427a1f51a3e7e1df",
					"jsonFile" : "target-water_tower-8ac54a9e5d1a94a955f8.json",
					"name" : "water_tower",
					"projectIndex" : 0
				},
				{
					"directoryIndex" : 0,
					"id" : "willowgarage::@6890427a1f51a3e7e1df",
					"jsonFile" : "target-willowgarage-bac9fbad15c2f8d64160.json",
					"name" : "willowgarage",
					"projectIndex" : 0
				},
				{
					"directoryIndex" : 0,
					"id" : "winding_valley_heightmap::@6890427a1f51a3e7e1df",
					"jsonFile" : "target-winding_valley_heightmap-8a1b4a193b0df7666e8a.json",
					"name" : "winding_valley_heightmap",
					"projectIndex" : 0
				},
				{
					"directoryIndex" : 0,
					"id" : "wood_block_10_2_1cm::@6890427a1f51a3e7e1df",
					"jsonFile" : "target-wood_block_10_2_1cm-3b131b7e7f778a67089a.json",
					"name" : "wood_block_10_2_1cm",
					"projectIndex" : 0
				},
				{
					"directoryIndex" : 0,
					"id" : "wood_cube_10cm::@6890427a1f51a3e7e1df",
					"jsonFile" : "target-wood_cube_10cm-9e4d89de15d40f895875.json",
					"name" : "wood_cube_10cm",
					"projectIndex" : 0
				},
				{
					"directoryIndex" : 0,
					"id" : "wood_cube_2_5cm::@6890427a1f51a3e7e1df",
					"jsonFile" : "target-wood_cube_2_5cm-0ca5b7defbad4d503ab8.json",
					"name" : "wood_cube_2_5cm",
					"projectIndex" : 0
				},
				{
					"directoryIndex" : 0,
					"id" : "wood_cube_5cm::@6890427a1f51a3e7e1df",
					"jsonFile" : "target-wood_cube_5cm-eca0b2f7c9476524b857.json",
					"name" : "wood_cube_5cm",
					"projectIndex" : 0
				},
				{
					"directoryIndex" : 0,
					"id" : "wood_cube_7_5cm::@6890427a1f51a3e7e1df",
					"jsonFile" : "target-wood_cube_7_5cm-284d0c115b3c68dd5ec9.json",
					"name" : "wood_cube_7_5cm",
					"projectIndex" : 0
				},
				{
					"directoryIndex" : 0,
					"id" : "wooden_board::@6890427a1f51a3e7e1df",
					"jsonFile" : "target-wooden_board-cd7eaf2d15407b75aa5c.json",
					"name" : "wooden_board",
					"projectIndex" : 0
				},
				{
					"directoryIndex" : 0,
					"id" : "wooden_case::@6890427a1f51a3e7e1df",
					"jsonFile" : "target-wooden_case-315289f20dc592e11420.json",
					"name" : "wooden_case",
					"projectIndex" : 0
				},
				{
					"directoryIndex" : 0,
					"id" : "wooden_case_metal_peg::@6890427a1f51a3e7e1df",
					"jsonFile" : "target-wooden_case_metal_peg-0274787152e52a51e054.json",
					"name" : "wooden_case_metal_peg",
					"projectIndex" : 0
				},
				{
					"directoryIndex" : 0,
					"id" : "wooden_case_wooden_peg::@6890427a1f51a3e7e1df",
					"jsonFile" : "target-wooden_case_wooden_peg-58d1ac90abb9e6dff17c.json",
					"name" : "wooden_case_wooden_peg",
					"projectIndex" : 0
				},
				{
					"directoryIndex" : 0,
					"id" : "wooden_peg::@6890427a1f51a3e7e1df",
					"jsonFile" : "target-wooden_peg-f9934d3c4ae04547d6f8.json",
					"name" : "wooden_peg",
					"projectIndex" : 0
				},
				{
					"directoryIndex" : 0,
					"id" : "wooden_peg_board::@6890427a1f51a3e7e1df",
					"jsonFile" : "target-wooden_peg_board-90b34dce27abb401f7b2.json",
					"name" : "wooden_peg_board",
					"projectIndex" : 0
				}
			]
		}
	],
	"kind" : "codemodel",
	"paths" : 
	{
		"build" : "/home/elena/Documentos/GitHub/IR2136/build/gazebo_models",
		"source" : "/home/elena/Documentos/GitHub/IR2136/gazebo_models-master"
	},
	"version" : 
	{
		"major" : 2,
		"minor" : 3
	}
}
